{
 "added": [
  {
   "symbol": "NVN.P",
   "name": "Navion Capital II Inc.",
   "exchange": "TSXV",
   "yahoo_symbol": "NVN.P.V",
   "instruments": [
    {
     "name": "Navion Capital II Inc.",
     "symbol": "NVN.P"
    }
   ]
  },
  {
   "symbol": "CRML",
   "name": "Critical Metals Corp. - Ordinary Shares",
   "exchange": "NASDAQ Global MarketSM",
   "yahoo_symbol": "CRML"
  },
  {
   "symbol": "CRMLW",
   "name": "Critical Metals Corp. - Warrants",
   "exchange": "NASDAQ Capital Market",
   "yahoo_symbol": "CRMLW"
  },
  {
   "symbol": "RYDE",
   "name": "Ryde Group Ltd. Class A Ordinary Shares",
   "exchange": "NYSE MKT",
   "yahoo_symbol": "RYDE"
  },
  {
   "symbol": "SYF$B",
   "name": "Synchrony Financial Depositary Shares Each Representing a 1/40th Interest in a Share of 8.250% Fixed Rate Reset Non-Cumulative Perpetual Preferred Stock, Series B",
   "exchange": "NYSE",
   "yahoo_symbol": "SYF$B"
  }
 ],
 "removed": [
  {
   "symbol": "MDRX",
   "name": "Veradigm Inc. - common stock",
   "exchange": "NASDAQ Global Select MarketSM",
   "yahoo_symbol": "MDRX"
  },
  {
   "symbol": "CRGE",
   "name": "Charge Enterprises, Inc. - Common Stock",
   "exchange": "NASDAQ Capital Market",
   "yahoo_symbol": "CRGE"
  },
  {
   "symbol": "AZ",
   "name": "A2Z Smart Technologies Corp.",
   "exchange": "TSXV",
   "yahoo_symbol": "AZ.V",
   "instruments": [
    {
     "name": "A2Z Smart Technologies Corp.",
     "symbol": "AZ"
    }
   ]
  }
 ]
}