{
 "added": [
  {
   "symbol": "APM",
   "name": "Andean Precious Metals Corp.",
   "exchange": "TSX",
   "yahoo_symbol": "APM.TO",
   "instruments": [
    {
     "name": "Andean Prec Meta Cor",
     "symbol": "APM"
    }
   ]
  },
  {
   "symbol": "MASK",
   "name": "3 E Network Technology Group Ltd - Class A Ordinary Shares",
   "exchange": "NASDAQ Capital Market",
   "yahoo_symbol": "MASK"
  }
 ],
 "removed": [
  {
   "symbol": "APM",
   "name": "Andean Precious Metals Corp.",
   "exchange": "TSXV",
   "yahoo_symbol": "APM.V",
   "instruments": [
    {
     "name": "Andean Precious Metals Corp.",
     "symbol": "APM"
    }
   ]
  },
  {
   "symbol": "CSO",
   "name": "Corsa Coal Corp.",
   "exchange": "TSXV",
   "yahoo_symbol": "CSO.V",
   "instruments": [
    {
     "name": "Corsa Coal Corp.",
     "symbol": "CSO"
    }
   ]
  },
  {
   "symbol": "KAC.P",
   "name": "Kalon Acquisition Corp.",
   "exchange": "TSXV",
   "yahoo_symbol": "KAC.P.V",
   "instruments": [
    {
     "name": "Kalon Acquisition Corp.",
     "symbol": "KAC.P"
    }
   ]
  }
 ]
}